carboncli.py
carbon/__init__.py
carbon/calculator.py
carbon/exceptions.py
carbon/services.py
carbon/statistics.py
carbon_calculator-0.1.2.dist-info/LICENSE
carbon_calculator-0.1.2.dist-info/METADATA
carbon_calculator-0.1.2.dist-info/WHEEL
carbon_calculator-0.1.2.dist-info/entry_points.txt
carbon_calculator-0.1.2.dist-info/top_level.txt
carbon_calculator-0.1.2.dist-info/RECORD
