Metadata-Version: 2.1
Name: carbon-calculator
Version: 0.1.2
Summary: Carbon Calculator
Home-page: https://github.com/gpirrotta/carbon-calculator
Author: Giovanni Pirrotta
Author-email: giovanni.pirrotta@gmail.com
License: MIT license
Keywords: green,environment,carbon,co2,pollution
Platform: any
Classifier: Development Status :: 4 - Beta
Classifier: Intended Audience :: Developers
Classifier: License :: OSI Approved :: MIT License
Classifier: Natural Language :: English
Classifier: Programming Language :: Python :: 3
Classifier: Programming Language :: Python :: 3.6
Classifier: Programming Language :: Python :: 3.7
Classifier: Programming Language :: Python :: 3.8
Classifier: Programming Language :: Python :: 3.9
Requires-Python: >=3.6
License-File: LICENSE
Requires-Dist: validators (==0.18.2)
